evol/__init__.py
evol/conditions.py
evol/evolution.py
evol/exceptions.py
evol/individual.py
evol/logger.py
evol/population.py
evol/serialization.py
evol/step.py
evol/utils.py
evol/helpers/__init__.py
evol/helpers/groups.py
evol/helpers/pickers.py
evol/helpers/utils.py
evol/helpers/combiners/__init__.py
evol/helpers/combiners/permutation.py
evol/helpers/combiners/utils.py
evol/helpers/mutators/__init__.py
evol/helpers/mutators/permutation.py
evol/problems/__init__.py
evol/problems/problem.py
evol/problems/functions/__init__.py
evol/problems/functions/variableinput.py
evol/problems/routing/__init__.py
evol/problems/routing/coordinates.py
evol/problems/routing/magicsanta.py
evol/problems/routing/tsp.py
evol-0.5.3.dist-info/LICENSE
evol-0.5.3.dist-info/METADATA
evol-0.5.3.dist-info/WHEEL
evol-0.5.3.dist-info/top_level.txt
evol-0.5.3.dist-info/RECORD
