Metadata-Version: 2.1
Name: evol
Version: 0.5.3
Summary: A Grammar for Evolutionary Algorithms and Heuristics
Home-page: https://github.com/godatadriven/evol
Author: ['Vincent D. Warmerdam', 'Rogier van der Geer']
Author-email: vincentwarmerdam@gmail.com
License: MIT License
Keywords: genetic,algorithms,heuristics
Platform: UNKNOWN
Classifier: Intended Audience :: Developers
Classifier: Intended Audience :: Science/Research
Classifier: Programming Language :: Python :: 3.6
Classifier: Development Status :: 3 - Alpha
Classifier: License :: OSI Approved :: MIT License
Classifier: Topic :: Scientific/Engineering
Classifier: Topic :: Scientific/Engineering :: Artificial Intelligence
Requires-Python: >=3.6
Requires-Dist: multiprocess (>=0.70.6.1)
Provides-Extra: dev
Requires-Dist: attrs (==19.1.0) ; extra == 'dev'
Requires-Dist: flake8 (>=3.7.9) ; extra == 'dev'
Requires-Dist: pytest (>=3.3.1) ; extra == 'dev'
Provides-Extra: docs
Requires-Dist: Sphinx (>=2.0.0) ; extra == 'docs'
Requires-Dist: sphinx-rtd-theme ; extra == 'docs'
